vjobs_vdnjobs/__init__.py
vjobs_vdnjobs/main.py
vjobs_vdnjobs-0.1.2.dist-info/LICENSE
vjobs_vdnjobs-0.1.2.dist-info/METADATA
vjobs_vdnjobs-0.1.2.dist-info/WHEEL
vjobs_vdnjobs-0.1.2.dist-info/top_level.txt
vjobs_vdnjobs-0.1.2.dist-info/RECORD
