Metadata-Version: 2.1
Name: vjobs-vdnjobs
Version: 0.1.2
Summary: Collects jobs from vdnjobs.ca for vjobs
Home-page: https://gitlab.com/flaxking/vjobs-vdnjobs
Author: flaxking
Author-email: flaxking@digitalnostril.com
License: UNKNOWN
Platform: UNKNOWN
Classifier: Programming Language :: Python :: 3
Classifier: License :: OSI Approved :: GNU General Public License v3 (GPLv3)
Classifier: Operating System :: OS Independent
Requires-Dist: vdnjobs-client
Requires-Dist: vjobs (>=0.1.0)
